odoo/addons/shopinvader_pos/README.rst
odoo/addons/shopinvader_pos/__init__.py
odoo/addons/shopinvader_pos/__manifest__.py
odoo/addons/shopinvader_pos/i18n/shopinvader_pos.pot
odoo/addons/shopinvader_pos/readme/CONTRIBUTORS.rst
odoo/addons/shopinvader_pos/readme/DESCRIPTION.rst
odoo/addons/shopinvader_pos/readme/USAGE.rst
odoo/addons/shopinvader_pos/services/__init__.py
odoo/addons/shopinvader_pos/services/shopinvader_pos.py
odoo/addons/shopinvader_pos/static/description/index.html
odoo/addons/shopinvader_pos/tests/__init__.py
odoo/addons/shopinvader_pos/tests/test_shopinvader_pos.py
odoo14_addon_shopinvader_pos-14.0.2.2.1.dev5.dist-info/METADATA
odoo14_addon_shopinvader_pos-14.0.2.2.1.dev5.dist-info/WHEEL
odoo14_addon_shopinvader_pos-14.0.2.2.1.dev5.dist-info/top_level.txt
odoo14_addon_shopinvader_pos-14.0.2.2.1.dev5.dist-info/RECORD
